{
  "project_info": {
    "project_number": "1063072137159",
    "project_id": "bmcsports2025",
    "storage_bucket": "bmcsports2025.firebasestorage.app"
  },
  "client": [
    {
      "client_info": {
        "mobilesdk_app_id": "1:1063072137159:android:927e59ec5df2be0782a3e2",
        "android_client_info": {
          "package_name": "com.example.bmcsports"
        }
      },
      "oauth_client": [],
      "api_key": [
        {
          "current_key": "AIzaSyCuo0tAm1UwouV5Cgjn55_bpAC72iIKwG4"
        }
      ],
      "services": {
        "appinvite_service": {
          "other_platform_oauth_client": []
        }
      }
    }
  ],
  "configuration_version": "1"
}